pypper/__init__.py
pypper/cloud_handling/aws/s3.py
pypper/cloud_handling/gcp/bigquery.py
pypper/cloud_handling/gcp/google_bucket.py
pypper/data_crawling/__init__.py
pypper/data_crawling/base_crawling.py
pypper/data_crawling/image_crawling.py
pypper/data_processing/__init__.py
pypper/data_processing/audio/speech_processing.py
pypper/data_processing/datetime/datetime_processing.py
pypper/data_processing/json/json_normalize.py
pypper/data_processing/nlp/tokenizing.py
pypper/data_processing/tabular/df_processing.py
pypper/data_processing/text/text_processing.py
pypper/data_processing/text/translation.py
pypper/file_handling/__init__.py
pypper/file_handling/csv_handling.py
pypper/file_handling/file_system_handling.py
pypper/file_handling/pdf_handling.py
pypper/mongodb_handling/data_process.py
pypper/utils/__init__.py
pypper/utils/enums.py
pypper-0.1.0.dist-info/LICENSE
pypper-0.1.0.dist-info/METADATA
pypper-0.1.0.dist-info/WHEEL
pypper-0.1.0.dist-info/RECORD
