Metadata-Version: 2.1
Name: pypper
Version: 0.1.0
Summary: 
Author: nguyen
Author-email: nguyenhainguyen2606@gmail.com
Requires-Python: >=3.9,<3.12
Classifier: Programming Language :: Python :: 3
Classifier: Programming Language :: Python :: 3.9
Classifier: Programming Language :: Python :: 3.10
Classifier: Programming Language :: Python :: 3.11
Requires-Dist: apache-airflow (>=2.8.3,<3.0.0)
Requires-Dist: beautifulsoup4 (>=4.12.3,<5.0.0)
Requires-Dist: boto3 (>=1.34.76,<2.0.0)
Requires-Dist: faster-whisper (>=1.0.1,<2.0.0)
Requires-Dist: gcloud (>=0.18.3,<0.19.0)
Requires-Dist: gcloud-aio-auth (>=5.2.2,<6.0.0)
Requires-Dist: google (>=3.0.0,<4.0.0)
Requires-Dist: google-cloud (>=0.34.0,<0.35.0)
Requires-Dist: google-cloud-bigquery (<3.13.0)
Requires-Dist: google-cloud-core (<2.3.3)
Requires-Dist: include (>=0.2.2,<0.3.0)
Requires-Dist: ndjson (>=0.3.1,<0.4.0)
Requires-Dist: numpy (>=1.26.4,<2.0.0)
Requires-Dist: pandas (>=2.2.1,<3.0.0)
Requires-Dist: pymongo (<=4.6.1)
Requires-Dist: pypdf (>=4.1.0,<5.0.0)
Requires-Dist: python-dotenv (>=1.0.1,<2.0.0)
Requires-Dist: ruff (>=0.3.5,<0.4.0)
Requires-Dist: selenium (>=4.18.1,<5.0.0)
Requires-Dist: tiktoken (>=0.6.0,<0.7.0)
Requires-Dist: translators (>=5.9.0,<6.0.0)
Project-URL: documentation, 
Project-URL: homepage, 
Project-URL: repository, https://github.com/NHNguyen94/pypper
